sqla_assigner-0.1.0.dist-info/METADATA
sqla_assigner-0.1.0.dist-info/WHEEL
sqla_assigner/__init__.py
sqla_assigner/base.py
sqla_assigner/py.typed
sqla_assigner-0.1.0.dist-info/RECORD
